synthhaku/__init__.py
synthhaku/__main__.py
synthhaku/codeblocks.py
synthhaku/cog.py
synthhaku/exception_handling.py
synthhaku/features/__init__.py
synthhaku/features/baseclass.py
synthhaku/features/filesystem.py
synthhaku/features/guild.py
synthhaku/features/invocation.py
synthhaku/features/management.py
synthhaku/features/python.py
synthhaku/features/root_command.py
synthhaku/features/scaffolds/c/main.c
synthhaku/features/scaffolds/cargo/Cargo.toml
synthhaku/features/scaffolds/cargo/src/main.rs
synthhaku/features/scaffolds/cpp/main.cpp
synthhaku/features/scaffolds/npm/index.js
synthhaku/features/scaffolds/npm/package.json
synthhaku/features/scaffolds/pyright/main.py
synthhaku/features/scaffolds/pyright/pyrightconfig.json
synthhaku/features/shell.py
synthhaku/features/voice.py
synthhaku/features/youtube.py
synthhaku/flags.py
synthhaku/formatting.py
synthhaku/functools.py
synthhaku/hljs.py
synthhaku/math.py
synthhaku/meta.py
synthhaku/models.py
synthhaku/modules.py
synthhaku/paginators.py
synthhaku/py.typed
synthhaku/repl/__init__.py
synthhaku/repl/compilation.py
synthhaku/repl/disassembly.py
synthhaku/repl/inspections.py
synthhaku/repl/repl_builtins.py
synthhaku/repl/scope.py
synthhaku/repl/walkers.py
synthhaku/shell.py
synthhaku/types.py
synthhaku-2.6.1.dist-info/LICENSE
synthhaku-2.6.1.dist-info/METADATA
synthhaku-2.6.1.dist-info/WHEEL
synthhaku-2.6.1.dist-info/RECORD
