Metadata-Version: 2.1
Name: synthhaku
Version: 2.6.1
Summary: a debugging and utility extension for disnake bots
Author: Synth Team
Requires-Python: >=3.8.0
Classifier: Programming Language :: Python :: 3
Classifier: Programming Language :: Python :: 3.8
Classifier: Programming Language :: Python :: 3.9
Classifier: Programming Language :: Python :: 3.10
Classifier: Programming Language :: Python :: 3.11
Classifier: Programming Language :: Python :: 3.12
